quplots/__about__.py
quplots/__init__.py
quplots/electron/coordinates.py
quplots/electron/electron.py
quplots/electron/radial.py
quplots/electron/sphericalHarmonics.py
quplots/electron/waveFunction.py
quplots/hibrydization/hybridization.py
quplots/hibrydization/sp.py
quplots/hibrydization/sp2.py
quplots/hibrydization/sp2d.py
quplots/hibrydization/sp3.py
quplots/hibrydization/sp3d.py
quplots/hibrydization/sp3d2.py
quplots/plots/plots.py
quplots-0.0.1.dist-info/METADATA
quplots-0.0.1.dist-info/WHEEL
quplots-0.0.1.dist-info/licenses/LICENSE.txt
quplots-0.0.1.dist-info/RECORD
